packagehim/__init__.py
packagehim/pkg_guess_number.py
packagehim/pkg_weight_conversion.py
GuessConversionPkg-0.1.0.dist-info/METADATA
GuessConversionPkg-0.1.0.dist-info/WHEEL
GuessConversionPkg-0.1.0.dist-info/top_level.txt
GuessConversionPkg-0.1.0.dist-info/RECORD
