Metadata-Version: 2.1
Name: GuessConversionPkg
Version: 0.1.0
Summary: Learn to create python package
Author: Himm (Ibrahim Aryan Faridzi)
Author-email: <ibra12@test.com>
Keywords: python,guess,number,weight,conversion,guess number,weight conversion
Classifier: Development Status :: 1 - Planning
Classifier: Intended Audience :: Developers
Classifier: Programming Language :: Python :: 3
Classifier: Operating System :: Unix
Classifier: Operating System :: MacOS :: MacOS X
Classifier: Operating System :: Microsoft :: Windows
